{
    "data": {
        "author": "Sam Cappleman-Lynes",
        "grid": [
            [
                {},
                {},
                {},
                {},
                {},
                {},
                {},
                {},
                {}
            ],
            [
                {},
                {},
                {},
                {},
                {},
                {},
                {},
                {},
                {}
            ],
            [
                {},
                {},
                {},
                {
                    "given": true,
                    "value": 2
                },
                {},
                {
                    "given": true,
                    "value": 3
                },
                {},
                {},
                {}
            ],
            [
                {},
                {},
                {
                    "given": true,
                    "value": 1
                },
                {},
                {},
                {},
                {
                    "given": true,
                    "value": 4
                },
                {},
                {}
            ],
            [
                {},
                {},
                {},
                {},
                {
                    "given": true,
                    "value": 9
                },
                {},
                {},
                {},
                {}
            ],
            [
                {},
                {},
                {
                    "given": true,
                    "value": 8
                },
                {},
                {},
                {},
                {
                    "given": true,
                    "value": 5
                },
                {},
                {}
            ],
            [
                {},
                {},
                {},
                {
                    "given": true,
                    "value": 7
                },
                {},
                {
                    "given": true,
                    "value": 6
                },
                {},
                {},
                {}
            ],
            [
                {},
                {},
                {},
                {},
                {},
                {},
                {},
                {},
                {}
            ],
            [
                {},
                {},
                {},
                {},
                {},
                {},
                {},
                {},
                {}
            ]
        ],
        "ruleset": "Normal Sudoku rules apply. Each number in the grid represents a building of that height, and clues outside the grid indicate how many buildings are visible when looking from that point along the corresponding row or column. A building is visible when there are no taller buildings before it.",
        "size": 9,
        "text": [
            {
                "cells": [
                    "R0C5"
                ],
                "fontC": "#000000",
                "size": 0.75,
                "value": "5"
            },
            {
                "cells": [
                    "R0C7"
                ],
                "fontC": "#000000",
                "size": 0.75,
                "value": "5"
            },
            {
                "cells": [
                    "R1C10"
                ],
                "fontC": "#000000",
                "size": 0.75,
                "value": "3"
            },
            {
                "cells": [
                    "R4C10"
                ],
                "fontC": "#000000",
                "size": 0.75,
                "value": "6"
            },
            {
                "cells": [
                    "R7C10"
                ],
                "fontC": "#000000",
                "size": 0.75,
                "value": "7"
            },
            {
                "cells": [
                    "R10C5"
                ],
                "fontC": "#000000",
                "size": 0.75,
                "value": "5"
            },
            {
                "cells": [
                    "R10C3"
                ],
                "fontC": "#000000",
                "size": 0.75,
                "value": "3"
            },
            {
                "cells": [
                    "R9C0"
                ],
                "fontC": "#000000",
                "size": 0.75,
                "value": "4"
            },
            {
                "cells": [
                    "R6C0"
                ],
                "fontC": "#000000",
                "size": 0.75,
                "value": "4"
            },
            {
                "cells": [
                    "R3C0"
                ],
                "fontC": "#000000",
                "size": 0.75,
                "value": "7"
            }
        ],
        "title": "Skyscrapers Sudoku"
    },
    "url": "https://f-puzzles.com/?id=29m97ua7"
}